guillotina_gcloudstorage/__init__.py
guillotina_gcloudstorage/interfaces.py
guillotina_gcloudstorage/py.typed
guillotina_gcloudstorage/storage.py
guillotina_gcloudstorage/tests/__init__.py
guillotina_gcloudstorage/tests/conftest.py
guillotina_gcloudstorage/tests/fixtures.py
guillotina_gcloudstorage/tests/test_storage.py
guillotina_gcloudstorage-6.0.2.dist-info/LICENSE
guillotina_gcloudstorage-6.0.2.dist-info/METADATA
guillotina_gcloudstorage-6.0.2.dist-info/WHEEL
guillotina_gcloudstorage-6.0.2.dist-info/entry_points.txt
guillotina_gcloudstorage-6.0.2.dist-info/top_level.txt
guillotina_gcloudstorage-6.0.2.dist-info/zip-safe
guillotina_gcloudstorage-6.0.2.dist-info/RECORD
