Metadata-Version: 2.1
Name: guillotina-gcloudstorage
Version: 6.0.2
Summary: guillotina gcloud storage support
Home-page: https://pypi.python.org/pypi/guillotina_gcloudstorage
Author: Ramon Navarro Bosch
Author-email: ramon@plone.org
License: GPL version 3
Keywords: guillotina async cloud storage
Platform: UNKNOWN
Classifier: Programming Language :: Python :: 3.7
Classifier: Topic :: Software Development :: Libraries :: Python Modules
Requires-Dist: setuptools
Requires-Dist: guillotina (>=5.3.48)
Requires-Dist: protobuf
Requires-Dist: oauth2client
Requires-Dist: google-cloud-storage
Requires-Dist: gcloud
Requires-Dist: ujson
Requires-Dist: backoff
Provides-Extra: test
Requires-Dist: pytest ; extra == 'test'
Requires-Dist: pytest-docker-fixtures ; extra == 'test'
Requires-Dist: pytest-aiohttp (>=0.3.0) ; extra == 'test'
